mdx_linkify/__init__.py
mdx_linkify/mdx_linkify.py
mdx_linkify/tests.py
mdx_linkify-2.0.dist-info/LICENSE
mdx_linkify-2.0.dist-info/METADATA
mdx_linkify-2.0.dist-info/WHEEL
mdx_linkify-2.0.dist-info/top_level.txt
mdx_linkify-2.0.dist-info/RECORD
