Metadata-Version: 2.1
Name: mdx-linkify
Version: 2.0
Summary: Link recognition for Python Markdown
Home-page: https://github.com/daGrevis/mdx_linkify
Author: Raitis (daGrevis) Stengrevics
Author-email: dagrevis@gmail.com
License: MIT
Keywords: markdown links
Platform: UNKNOWN
Classifier: Topic :: Text Processing :: Markup
Classifier: Topic :: Utilities
Classifier: Programming Language :: Python :: 2.7
Classifier: Programming Language :: Python :: 3.8
Classifier: Programming Language :: Python :: Implementation :: PyPy
Classifier: Development Status :: 4 - Beta
Classifier: License :: OSI Approved :: MIT License
Requires-Dist: Markdown (>=3.0)
Requires-Dist: bleach (>=3.1.0)
